djazz_cli/__init__.py
djazz_cli/main.py
djazz_cli/templates/__init__.py
djazz_cli/templates/app_templates/default/__init__.py-tpl
djazz_cli/templates/app_templates/default/admin.py-tpl
djazz_cli/templates/app_templates/default/apps.py-tpl
djazz_cli/templates/app_templates/default/models.py-tpl
djazz_cli/templates/app_templates/default/tests.py-tpl
djazz_cli/templates/app_templates/default/urls.py-tpl
djazz_cli/templates/app_templates/default/views.py-tpl
djazz_cli/templates/app_templates/default/migrations/__init__.py-tpl
djazz_cli/templates/project_templates/default/manage.py-tpl
djazz_cli/templates/project_templates/default/project_name/__init__.py-tpl
djazz_cli/templates/project_templates/default/project_name/asgi.py-tpl
djazz_cli/templates/project_templates/default/project_name/settings.py-tpl
djazz_cli/templates/project_templates/default/project_name/urls.py-tpl
djazz_cli/templates/project_templates/default/project_name/wsgi.py-tpl
djazz_cli-0.1.2.dist-info/entry_points.txt
djazz_cli-0.1.2.dist-info/LICENSE
djazz_cli-0.1.2.dist-info/WHEEL
djazz_cli-0.1.2.dist-info/METADATA
djazz_cli-0.1.2.dist-info/RECORD
