Metadata-Version: 2.3
Name: djazz-cli
Version: 0.1.2
Summary: A CLI tool for Django development
Author-email: Azat <info@azat.ai>
Requires-Python: >=3.12
Requires-Dist: django>=5.0
Requires-Dist: typer>=0.15.1
Project-URL: Homepage, https://github.com/djazzcc/cli
Project-URL: Repository, https://github.com/djazzcc/cli
